resched
