Metadata-Version: 1.0
Name: Resched
Version: 0.1.12
Summary: super simple Redis scheduling & queueing in Python
Home-page: http://github.com/gamechanger/resched
Author: Kiril Savino
Author-email: kiril@gamechanger.io
License: BSD
Keywords: redis queue schedule
Platform: UNKNOWN
